fms_acceleration_foak/__init__.py
fms_acceleration_foak/framework_plugin_fast_kernels.py
fms_acceleration_foak/utils.py
fms_acceleration_foak/fused_ops/__init__.py
fms_acceleration_foak/fused_ops/liger_ce/__init__.py
fms_acceleration_foak/fused_ops/liger_ce/cross_entropy.py
fms_acceleration_foak/fused_ops/liger_ce/fused_linear_cross_entropy_loss.py
fms_acceleration_foak/fused_ops/unsloth_lora/__init__.py
fms_acceleration_foak/fused_ops/unsloth_lora/geglu.py
fms_acceleration_foak/fused_ops/unsloth_lora/swiglu.py
fms_acceleration_foak/fused_ops/unsloth_lora/utils.py
fms_acceleration_foak/fused_ops/unsloth_lora/bnb/__init__.py
fms_acceleration_foak/fused_ops/unsloth_lora/bnb/fast_lora.py
fms_acceleration_foak/fused_ops/unsloth_lora/gptq/__init__.py
fms_acceleration_foak/fused_ops/unsloth_lora/gptq/fast_lora.py
fms_acceleration_foak/fused_ops/unsloth_lora/gptq/triton/__init__.py
fms_acceleration_foak/fused_ops/unsloth_lora/gptq/triton/kernels.py
fms_acceleration_foak/fused_ops/unsloth_lora/gptq/triton/layers.py
fms_acceleration_foak/fused_ops/unsloth_lora/gptq/triton/tuner.py
fms_acceleration_foak/kernels/__init__.py
fms_acceleration_foak/kernels/unsloth/__init__.py
fms_acceleration_foak/kernels/unsloth/cross_entropy_loss.py
fms_acceleration_foak/kernels/unsloth/rms_layernorm.py
fms_acceleration_foak/kernels/unsloth/rope_embedding.py
fms_acceleration_foak/kernels/unsloth/utils.py
fms_acceleration_foak/models/__init__.py
fms_acceleration_foak/models/gpt_bigcode.py
fms_acceleration_foak/models/granite.py
fms_acceleration_foak/models/granitemoe.py
fms_acceleration_foak/models/granitemoehybrid.py
fms_acceleration_foak/models/granitemoeshared.py
fms_acceleration_foak/models/llama.py
fms_acceleration_foak/models/mistral.py
fms_acceleration_foak/models/mixtral.py
fms_acceleration_foak/models/utils.py
fms_acceleration_foak-0.7.2.dist-info/METADATA
fms_acceleration_foak-0.7.2.dist-info/WHEEL
fms_acceleration_foak-0.7.2.dist-info/RECORD
