Metadata-Version: 2.4
Name: fms-acceleration-foak
Version: 0.7.2
Summary: FMS Acceleration using Fused Operations and Kernels
Author-email: Fabian Lim <flim@sg.ibm.com>, Aaron Chew <aaron.chew1@ibm.com>
License: Apache-2.0
Keywords: acceleration,fms-hf-tuning,fused-ops,triton
Classifier: Development Status :: 4 - Beta
Classifier: License :: OSI Approved :: Apache Software License
Classifier: Programming Language :: Python :: 3
Classifier: Programming Language :: Python :: 3.9
Classifier: Programming Language :: Python :: 3.10
Classifier: Programming Language :: Python :: 3.11
Requires-Python: ~=3.9
